{
  "type": "minecraft:crafting_shapeless",
  "category": "misc",
  "ingredients": [
    {
      "item": "minecraft:glass_bottle"
    },
    {
      "type": "neoforge:components",
      "components": {
        "vampirism:bottle_blood": {
          "blood": 9
        }
      },
      "items": "vampirism:blood_bottle"
    },
    [
      {
        "item": "minecraft:apple"
      },
      {
        "item": "minecraft:sweet_berries"
      },
      {
        "item": "minecraft:glow_berries"
      },
      {
        "item": "vampirism:cursed_roots"
      },
      {
        "item": "vampirism:dark_spruce_leaves"
      },
      {
        "item": "vampirism:dark_spruce_sapling"
      },
      {
        "item": "vampirism:cursed_spruce_sapling"
      }
    ]
  ],
  "result": {
    "count": 2,
    "id": "vampiresdelight:blood_syrup"
  }
}